shapeGMM/__init__.py
shapeGMM/_gmm_shapes_uniform_library.py
shapeGMM/_gmm_shapes_weighted_library.py
shapeGMM/_kmeans_shapes.py
shapeGMM/_traj_tools.py
shapeGMM/gmm_shapes.py
shapeGMM/gmm_shapes_uniform_library.py
shapeGMM/gmm_shapes_weighted_library.py
shapeGMM/kmeans_shapes.py
shapeGMM/traj_tools.py
shapeGMM-0.0.5.dist-info/LICENSE
shapeGMM-0.0.5.dist-info/METADATA
shapeGMM-0.0.5.dist-info/WHEEL
shapeGMM-0.0.5.dist-info/top_level.txt
shapeGMM-0.0.5.dist-info/RECORD
