Metadata-Version: 2.1
Name: shapeGMM
Version: 0.0.5
Summary: Gaussian Mixture Model clustering in size-and-shape space
Home-page: https://github.com/mccullaghlab/GMM-Positions
Author: Martin McCullagh
Author-email: martin.mccullagh@okstate.edu
License: MIT
Project-URL: Bug Tracker, https://github.com/mccullaghlab/GMM-Positions/issues
Platform: UNKNOWN
Classifier: Programming Language :: Python :: 3
Classifier: License :: OSI Approved :: MIT License
Classifier: Operating System :: OS Independent
Requires-Python: >=3.6
License-File: LICENSE
Requires-Dist: numpy
Requires-Dist: numba
Requires-Dist: sklearn
